prina/__init__.py
prina/utils.py
prina/utils_test.py
prina/version.py
prina-0.1.3.dist-info/LICENSE
prina-0.1.3.dist-info/METADATA
prina-0.1.3.dist-info/WHEEL
prina-0.1.3.dist-info/top_level.txt
prina-0.1.3.dist-info/zip-safe
prina-0.1.3.dist-info/RECORD
