Metadata-Version: 2.1
Name: prina
Version: 0.1.3
Summary: print python variable with the variable name.
Home-page: https://github.com/Ailln/prina
Author: Ailln
Author-email: kinggreenhall@gmail.com
License: MIT License
Platform: UNKNOWN
Classifier: Programming Language :: Python :: 3
Classifier: License :: OSI Approved :: MIT License
Classifier: Operating System :: OS Independent
Requires-Dist: setuptools (>=40.6.3)
